sequencegenerator/IUPACController.py
sequencegenerator/__init__.py
sequencegenerator/__main__.py
sequencegenerator/generatePool.py
sequencegenerator/py.typed
sequencegenerator-0.4.0.dist-info/entry_points.txt
sequencegenerator-0.4.0.dist-info/LICENSE
sequencegenerator-0.4.0.dist-info/WHEEL
sequencegenerator-0.4.0.dist-info/METADATA
sequencegenerator-0.4.0.dist-info/RECORD
