Metadata-Version: 2.1
Name: sequencegenerator
Version: 0.4.0
Summary: sequencegenerator
Home-page: https://github.com/sequencegenerator/sequencegenerator
License: BSD-3
Author: sequencegenerator
Author-email: hello@sequencegenerator.com
Requires-Python: >=3.9,<4.0
Classifier: Development Status :: 3 - Alpha
Classifier: Intended Audience :: Developers
Classifier: License :: OSI Approved :: BSD License
Classifier: License :: Other/Proprietary License
Classifier: Operating System :: OS Independent
Classifier: Programming Language :: Python :: 3
Classifier: Programming Language :: Python :: 3.9
Classifier: Topic :: Software Development :: Libraries :: Python Modules
Requires-Dist: biopython (>=1.79,<2.0)
Requires-Dist: rich (>=10.4.0,<11.0.0)
Requires-Dist: typer[all] (>=0.3.2,<0.4.0)
Project-URL: Repository, https://github.com/sequencegenerator/sequencegenerator
